mpsjobtracker/__init__.py
mpsjobtracker/job_monitor.py
mpsjobtracker/log_wrapper.py
mpsjobtracker/json_templates/job_tracker_init.json
mpsjobtracker/json_templates/main_step_list.json
mpsjobtracker/schemas/job.json
mpsjobtracker/tests/__init__.py
mpsjobtracker/tests/test_job_tracker.py
mpsjobtracker/trackers/__init__.py
mpsjobtracker/trackers/jobtracker.py
mpsjobtracker/trackers/validator.py
lts_mpsjobtracker_mongo-0.1.31.dist-info/METADATA
lts_mpsjobtracker_mongo-0.1.31.dist-info/WHEEL
lts_mpsjobtracker_mongo-0.1.31.dist-info/top_level.txt
lts_mpsjobtracker_mongo-0.1.31.dist-info/RECORD
