Metadata-Version: 2.1
Name: lts-mpsjobtracker-mongo
Version: 0.1.31
Summary: A job tracker management module
Home-page: https://github.huit.harvard.edu/LTS/mps-jobtracker
Author: Katie Amaral
Author-email: kathryn_amaral@harvard.edu
Classifier: Programming Language :: Python :: 3
Classifier: License :: OSI Approved :: MIT License
Classifier: Operating System :: OS Independent
Requires-Python: >=3.6
Requires-Dist: jsonschema
Requires-Dist: pymongo
Requires-Dist: pytest
Requires-Dist: tenacity
Requires-Dist: uuid
